[
	{
		"dateTime":"2014-04-25T00:00:00Z",
		"consumption":17.2
	},
	{
		"dateTime":"2014-04-25T00:01:00Z",
		"consumption":13.77
	},
	{
		"dateTime":"2014-04-25T00:02:00Z",
		"consumption":33.16
	},
	{
		"dateTime":"2014-04-25T00:03:00Z",
		"consumption":42.66
	},
	{
		"dateTime":"2014-04-25T00:04:00Z",
		"consumption":65.36
	},
	{
		"dateTime":"2014-04-25T00:05:00Z",
		"consumption":56.6
	},
	{
		"dateTime":"2014-04-25T00:06:00Z",
		"consumption":55.12
	},
	{
		"dateTime":"2014-04-25T00:07:00Z",
		"consumption":55.01
	},
	{
		"dateTime":"2014-04-25T00:08:00Z",
		"consumption":59.11
	},
	{
		"dateTime":"2014-04-25T00:09:00Z",
		"consumption":67.08
	},
	{
		"dateTime":"2014-04-25T00:10:00Z",
		"consumption":65.16
	},
	{
		"dateTime":"2014-04-25T00:11:00Z",
		"consumption":57.88
	},
	{
		"dateTime":"2014-04-25T00:12:00Z",
		"consumption":55.4
	},
	{
		"dateTime":"2014-04-25T00:13:00Z",
		"consumption":66.07
	},
	{
		"dateTime":"2014-04-25T00:14:00Z",
		"consumption":66.42
	},
	{
		"dateTime":"2014-04-25T00:15:00Z",
		"consumption":68.81
	},
	{
		"dateTime":"2014-04-25T00:16:00Z",
		"consumption":22.76
	},
	{
		"dateTime":"2014-04-25T00:17:00Z",
		"consumption":18.28
	},
	{
		"dateTime":"2014-04-25T00:18:00Z",
		"consumption":30.65
	},
	{
		"dateTime":"2014-04-25T00:19:00Z",
		"consumption":56.37
	},
	{
		"dateTime":"2014-04-25T00:20:00Z",
		"consumption":45.87
	},
	{
		"dateTime":"2014-04-25T00:21:00Z",
		"consumption":68.3
	},
	{
		"dateTime":"2014-04-25T00:22:00Z",
		"consumption":133.37
	},
	{
		"dateTime":"2014-04-25T00:23:00Z",
		"consumption":209.99
	},
	{
		"dateTime":"2014-04-25T00:24:00Z",
		"consumption":198.31
	},
	{
		"dateTime":"2014-04-25T00:25:00Z",
		"consumption":104.95
	},
	{
		"dateTime":"2014-04-25T00:26:00Z",
		"consumption":14.97
	},
	{
		"dateTime":"2014-04-25T00:27:00Z",
		"consumption":32.65
	},
	{
		"dateTime":"2014-04-25T00:28:00Z",
		"consumption":94.06
	},
	{
		"dateTime":"2014-04-25T00:29:00Z",
		"consumption":100.85
	},
	{
		"dateTime":"2014-04-25T00:30:00Z",
		"consumption":113.96
	},
	{
		"dateTime":"2014-04-25T00:31:00Z",
		"consumption":113.82
	},
	{
		"dateTime":"2014-04-25T00:32:00Z",
		"consumption":64.19
	},
	{
		"dateTime":"2014-04-25T00:33:00Z",
		"consumption":53.1
	},
	{
		"dateTime":"2014-04-25T00:34:00Z",
		"consumption":63.88
	},
	{
		"dateTime":"2014-04-25T00:35:00Z",
		"consumption":112.12
	},
	{
		"dateTime":"2014-04-25T00:36:00Z",
		"consumption":65.45
	},
	{
		"dateTime":"2014-04-25T00:37:00Z",
		"consumption":65.16
	},
	{
		"dateTime":"2014-04-25T00:38:00Z",
		"consumption":212.86
	},
	{
		"dateTime":"2014-04-25T00:39:00Z",
		"consumption":216.91
	},
	{
		"dateTime":"2014-04-25T00:40:00Z",
		"consumption":158.99
	},
	{
		"dateTime":"2014-04-25T00:41:00Z",
		"consumption":22.58
	},
	{
		"dateTime":"2014-04-25T00:42:00Z",
		"consumption":33.26
	},
	{
		"dateTime":"2014-04-25T00:43:00Z",
		"consumption":85.39
	},
	{
		"dateTime":"2014-04-25T00:44:00Z",
		"consumption":95.39
	},
	{
		"dateTime":"2014-04-25T00:45:00Z",
		"consumption":85.33
	},
	{
		"dateTime":"2014-04-25T00:46:00Z",
		"consumption":87.43
	},
	{
		"dateTime":"2014-04-25T00:47:00Z",
		"consumption":89.73
	},
	{
		"dateTime":"2014-04-25T00:48:00Z",
		"consumption":40.75
	},
	{
		"dateTime":"2014-04-25T00:49:00Z",
		"consumption":105.26
	},
	{
		"dateTime":"2014-04-25T00:50:00Z",
		"consumption":142.99
	},
	{
		"dateTime":"2014-04-25T00:51:00Z",
		"consumption":223.39
	},
	{
		"dateTime":"2014-04-25T00:52:00Z",
		"consumption":212.43
	},
	{
		"dateTime":"2014-04-25T00:53:00Z",
		"consumption":201.03
	},
	{
		"dateTime":"2014-04-25T00:54:00Z",
		"consumption":227.01
	},
	{
		"dateTime":"2014-04-25T00:55:00Z",
		"consumption":221.43
	},
	{
		"dateTime":"2014-04-25T00:56:00Z",
		"consumption":253.43
	},
	{
		"dateTime":"2014-04-25T00:57:00Z",
		"consumption":278.28
	},
	{
		"dateTime":"2014-04-25T00:58:00Z",
		"consumption":269.83
	},
	{
		"dateTime":"2014-04-25T00:59:00Z",
		"consumption":51.45
	}
]